{"cameraMode":{"drawMode":0,"name":"Shaded","section":"Shading Mode"},"sceneLighting":true,"audioPlay":false,"sceneViewState":{"m_AlwaysRefresh":false,"showFog":true,"showSkybox":true,"showFlares":true,"showImageEffects":true,"showParticleSystems":true,"showVisualEffectGraphs":true,"m_FxEnabled":true},"in2DMode":false,"pivot":{"x":0.11499331891536713,"y":2.592519998550415,"z":-3.009082794189453},"rotation":{"x":0.41210752725601199,"y":-0.052173763513565066,"z":0.023065518587827684,"w":0.9095471501350403},"size":1.0583081245422364,"orthographic":false}